ukb_loader/__init__.py
ukb_loader/all_dtypes.csv
ukb_loader/bed.py
ukb_loader/bed_test.py
ukb_loader/convert_all.py
ukb_loader/dtype_dict.py
ukb_loader/load.py
ukb_loader/load_test.py
ukb_loader/preprocess.py
ukb_loader/preprocess_test.py
ukb_loader/run_preprocess.py
ukb_loader/split.py
ukb_loader/split_test.py
ukb_loader-0.0.6.dist-info/LICENSE
ukb_loader-0.0.6.dist-info/METADATA
ukb_loader-0.0.6.dist-info/WHEEL
ukb_loader-0.0.6.dist-info/top_level.txt
ukb_loader-0.0.6.dist-info/RECORD
