Metadata-Version: 2.1
Name: ukb-loader
Version: 0.0.6
Summary: Package for fast loading of UK Biobank phenotype and genotype datasets
Home-page: https://github.com/alex-medvedev-msc/ukb_loader
Author: Aleksandr Medvedev
Author-email: aleksandr.medvedev@skoltech.ru
License: UNKNOWN
Project-URL: Bug Tracker, https://github.com/alex-medvedev-msc/ukb_loader/issues
Platform: UNKNOWN
Classifier: Programming Language :: Python :: 3
Classifier: License :: OSI Approved :: MIT License
Classifier: Operating System :: OS Independent
Requires-Python: >=3.6
License-File: LICENSE
Requires-Dist: pandas (>=1.2.0)
